magia/__init__.py
magia/bundle.py
magia/bus/__init__.py
magia/bus/axilite.py
magia/bus/axistream.py
magia/constants.py
magia/core.py
magia/external.py
magia/format/__init__.py
magia/format/fixed_point.py
magia/generator/__init__.py
magia/memory.py
magia/module.py
magia/std/__init__.py
magia/std/bundles.py
magia/std/encoding.py
magia/utils/__init__.py
magia_hdl-0.5.0.dist-info/LICENSE
magia_hdl-0.5.0.dist-info/METADATA
magia_hdl-0.5.0.dist-info/WHEEL
magia_hdl-0.5.0.dist-info/RECORD
